metantic/__init__.py
metantic/fields.py
metantic/omit.py
metantic/partial.py
metantic/take.py
metantic/util.py
metantic/fastapi/__init__.py
metantic/fastapi/deps.py
metantic/paths/__init__.py
metantic/paths/_builder.py
metantic/paths/_str.py
metantic/paths/_validate.py
metantic/paths/at.py
metantic/paths/path.py
metantic-0.2.0.dist-info/METADATA
metantic-0.2.0.dist-info/WHEEL
metantic-0.2.0.dist-info/top_level.txt
metantic-0.2.0.dist-info/RECORD
