Metadata-Version: 2.1
Name: metantic
Version: 0.2.0
Summary: Metaprogramming with pydantic Models (creating types from types) 
Author-email: Marcel Claramunt <marcel@moveread.com>
Requires-Python: >=3.10
Requires-Dist: pydantic
Requires-Dist: ramda
Provides-Extra: fastapi
Requires-Dist: fastapi ; extra == 'fastapi'
